chrono24/__init__.py
chrono24/api.py
chrono24/constants.py
chrono24/exceptions.py
chrono24/filters.py
chrono24/session.py
chrono24-0.3.2.dist-info/LICENSE
chrono24-0.3.2.dist-info/WHEEL
chrono24-0.3.2.dist-info/METADATA
chrono24-0.3.2.dist-info/RECORD
