Metadata-Version: 2.1
Name: chrono24
Version: 0.3.2
Summary: chrono24
Home-page: https://github.com/irahorecka/chrono24
Author: Ira Horecka
Author-email: ira89@icloud.com
Requires-Python: >=3.7
Classifier: Intended Audience :: Developers
Classifier: License :: OSI Approved :: MIT License
Classifier: Operating System :: OS Independent
Classifier: Programming Language :: Python :: 3.7
Classifier: Programming Language :: Python :: 3.8
Classifier: Programming Language :: Python :: 3.9
Classifier: Programming Language :: Python :: 3.10
Classifier: Programming Language :: Python :: 3.11
Classifier: Programming Language :: Python :: 3.12
Classifier: Topic :: Software Development :: Libraries
Classifier: Topic :: Utilities
Requires-Dist: beautifulsoup4>=4.11.0
Requires-Dist: faker>=30.0.0
Requires-Dist: requests>=2.28.0
Requires-Dist: tenacity>=8.2.0
